paymeuz/__init__.py
paymeuz/admin.py
paymeuz/apps.py
paymeuz/config.py
paymeuz/methods.py
paymeuz/models.py
paymeuz/serializers.py
paymeuz/tests.py
paymeuz/urls.py
paymeuz/views.py
paymeuz/migrations/0001_initial.py
paymeuz/migrations/0002_auto_20200826_1127.py
paymeuz/migrations/0003_remove_transaction_state.py
paymeuz/migrations/__init__.py
paymeuz-0.2.dist-info/LICENSE
paymeuz-0.2.dist-info/METADATA
paymeuz-0.2.dist-info/WHEEL
paymeuz-0.2.dist-info/top_level.txt
paymeuz-0.2.dist-info/RECORD
