Metadata-Version: 2.1
Name: paymeuz
Version: 0.2
Summary: paymeuz
Home-page: https://github.com/rajab-murod/paymeuz
Author: rajab-murod
Author-email: rajab.murod1995@gmail.com
License: UNKNOWN
Platform: UNKNOWN
Classifier: Programming Language :: Python :: 3
Classifier: License :: OSI Approved :: MIT License
Requires-Python: >=3.5
